hamstr1s/__init__.py
hamstr1s/addTaxa1s.py
hamstr1s/addTaxaHamstr.py
hamstr1s/addTaxon1s.py
hamstr1s/addTaxonHamstr.py
hamstr1s/checkData1s.py
hamstr1s/checkDataHamstr.py
hamstr1s/merge1sOutput.py
hamstr1s/mergePhyloprofileData.py
hamstr1s/remove1s.py
hamstr1s/runOneseq.py
hamstr1s/setup1s.py
hamstr1s/setupOneseq.py
hamstr1s/bin/Filehandler.pm
hamstr1s/bin/__init__.py
hamstr1s/bin/hamstr.pl
hamstr1s/bin/oneSeq.pl
hamstr1s/bin/run_genewise_hamstr.pm
hamstr1s/bin/translate.pl
hamstr1s/data/__init__.py
hamstr1s/data/infile.fa
hamstr1s/setup/__init__.py
hamstr1s/setup/indexTaxonomy.pl
hamstr1s/setup/install_lib.sh
hamstr1s/setup/setup.sh
hamstr1s/setup/setup_conda.sh
hamstr1s-2.0.4.dist-info/LICENCE
hamstr1s-2.0.4.dist-info/METADATA
hamstr1s-2.0.4.dist-info/WHEEL
hamstr1s-2.0.4.dist-info/entry_points.txt
hamstr1s-2.0.4.dist-info/top_level.txt
hamstr1s-2.0.4.dist-info/RECORD
